hungarian_loss/__init__.py
hungarian_loss/const.py
hungarian_loss/loss.py
hungarian_loss/ops.py
hungarian_loss/steps.py
hungarian_loss-1.0.1.dist-info/LICENSE
hungarian_loss-1.0.1.dist-info/METADATA
hungarian_loss-1.0.1.dist-info/WHEEL
hungarian_loss-1.0.1.dist-info/top_level.txt
hungarian_loss-1.0.1.dist-info/RECORD
