Metadata-Version: 2.1
Name: hungarian-loss
Version: 1.0.1
Summary: Package for computing the mean squared error between `y_true` and `y_pred` objects with prior assignment using the Hungarian algorithm.
Home-page: https://github.com/mmgalushka/hungarian-loss
Author: Mykola Galushka
Author-email: mm.galushka@gmail.com
Project-URL: Bug Tracker, https://github.com/mmgalushka/hungarian-loss/issues
Classifier: Intended Audience :: Developers
Classifier: License :: OSI Approved :: MIT License
Classifier: Operating System :: OS Independent
Classifier: Programming Language :: Python :: 3
Requires-Python: >=3.6
License-File: LICENSE
Requires-Dist: tensorflow >=2.4.0
